CHANGES.rst
LICENSE
MANIFEST.in
README.rst
requirements.txt
setup.py
tornado_expects/__init__.py
tornado_expects/matchers.py
tornado_expects.egg-info/PKG-INFO
tornado_expects.egg-info/SOURCES.txt
tornado_expects.egg-info/dependency_links.txt
tornado_expects.egg-info/requires.txt
tornado_expects.egg-info/top_level.txt