Metadata-Version: 1.1
Name: tornado-expects
Version: 0.1.0
Summary: Expects matchers for Tornado request and response objects
Home-page: https://github.com/jaimegildesagredo/tornado-expects
Author: Jaime Gil de Sagredo Luna
Author-email: jaimegildesagredo@gmail.com
License: Apache 2.0
Platform: UNKNOWN
Classifier: Development Status :: 3 - Alpha
Classifier: Intended Audience :: Developers
Classifier: Natural Language :: English
Classifier: Operating System :: OS Independent
Classifier: Programming Language :: Python
Classifier: Programming Language :: Python :: 2.7
Classifier: Programming Language :: Python :: 3.3
Classifier: Programming Language :: Python :: 3.4
Classifier: Programming Language :: Python :: Implementation :: PyPy
Classifier: Topic :: Software Development :: Libraries :: Python Modules
Classifier: License :: OSI Approved :: Apache Software License
